wtforms_widgets/__init__.py
wtforms_widgets/base_form.py
wtforms_widgets/widgets.py
wtforms_widgets/fields/__init__.py
wtforms_widgets/fields/core.py
wtforms_widgets/fields/custom.py
wtforms_widgets/fields/filters.py
wtforms_widgets/fields/validators.py
wtforms_widgets-1.0.9.dist-info/METADATA
wtforms_widgets-1.0.9.dist-info/WHEEL
wtforms_widgets-1.0.9.dist-info/licenses/LICENSE
wtforms_widgets-1.0.9.dist-info/RECORD
