Metadata-Version: 2.3
Name: wtforms-widgets
Version: 1.0.9
Summary: Decorator driven wtforms extension with Bootstrap 5 support for Flask
Project-URL: Repository, http://github.com/agdsn/wtforms-widgets/
Project-URL: Issues, http://github.com/agdsn/wtforms-widgets/issues
Author: The Pycroft Authors
License: Apache Software License
License-File: LICENSE
Classifier: Development Status :: 5 - Production/Stable
Classifier: Environment :: Web Environment
Classifier: Framework :: Flask
Classifier: Intended Audience :: System Administrators
Classifier: License :: OSI Approved :: Apache Software License
Classifier: Operating System :: OS Independent
Classifier: Programming Language :: Python :: 3.5
Classifier: Programming Language :: Python :: 3.6
Classifier: Programming Language :: Python :: 3.7
Requires-Python: >=3.5
Requires-Dist: flask
Requires-Dist: flask-wtf
Requires-Dist: markupsafe
Requires-Dist: wtforms
Provides-Extra: sql
Requires-Dist: wtforms-sqlalchemy; extra == 'sql'
